Metadata-Version: 2.1
Name: logged-groups
Version: 2.1.2
Summary: Per class logging tools
Home-page: http://rozhkovdmitrii.ru/
Author: Rozhkov Dmitrii
Author-email: rozhkovdmitrii@yandex.ru
License: GPL-3.0
Platform: UNKNOWN
Classifier: Programming Language :: Python :: 3
Classifier: License :: OSI Approved :: GNU General Public License v3 (GPLv3)
Classifier: Operating System :: OS Independent
License-File: LICENSE
